{
  "annotations": {
    "list": [
      {
        "builtIn": 1,
        "datasource": "-- Grafana --",
        "enable": true,
        "hide": true,
        "iconColor": "rgba(0, 211, 255, 1)",
        "name": "Annotations & Alerts",
        "type": "dashboard"
      }
    ]
  },
  "editable": true,
  "gnetId": null,
  "graphTooltip": 0,
  "id": 1,
  "links": [],
  "panels": [
    {
      "alert": {
        "alertRuleTags": {},
        "conditions": [
          {
            "evaluator": {
              "params": [],
              "type": "no_value"
            },
            "operator": {
              "type": "and"
            },
            "query": {
              "params": [
                "A",
                "5m",
                "now"
              ]
            },
            "reducer": {
              "params": [],
              "type": "last"
            },
            "type": "query"
          }
        ],
        "executionErrorState": "alerting",
        "for": "5m",
        "frequency": "1m",
        "handler": 1,
        "message": "No free disk space!",
        "name": "Disk free space alert",
        "noDataState": "no_data",
        "notifications": []
      },
      "aliasColors": {},
      "bars": false,
      "dashLength": 10,
      "dashes": false,
      "datasource": null,
      "fieldConfig": {
        "defaults": {
          "color": {},
          "custom": {},
          "thresholds": {
            "mode": "absolute",
            "steps": []
          },
          "unit": "short"
        },
        "overrides": []
      },
      "fill": 1,
      "fillGradient": 0,
      "gridPos": {
        "h": 8,
        "w": 12,
        "x": 0,
        "y": 0
      },
      "hiddenSeries": false,
      "id": 8,
      "legend": {
        "avg": false,
        "current": false,
        "max": false,
        "min": false,
        "show": true,
        "total": false,
        "values": false
      },
      "lines": true,
      "linewidth": 1,
      "nullPointMode": "null",
      "options": {
        "alertThreshold": true
      },
      "percentage": false,
      "pluginVersion": "7.4.0",
      "pointradius": 2,
      "points": false,
      "renderer": "flot",
      "seriesOverrides": [],
      "spaceLength": 10,
      "stack": false,
      "steppedLine": false,
      "targets": [
        {
          "expr": "node_filesystem_free_bytes{job=\"nodeexporter\",mountpoint=\"/\"}",
          "interval": "",
          "legendFormat": "Disk free",
          "refId": "A"
        }
      ],
      "thresholds": [],
      "timeFrom": null,
      "timeRegions": [],
      "timeShift": null,
      "title": "Disk free space",
      "tooltip": {
        "shared": true,
        "sort": 0,
        "value_type": "individual"
      },
      "type": "graph",
      "xaxis": {
        "buckets": null,
        "mode": "time",
        "name": null,
        "show": true,
        "values": []
      },
      "yaxes": [
        {
          "format": "short",
          "label": null,
          "logBase": 1,
          "max": null,
          "min": null,
          "show": true
        },
        {
          "format": "short",
          "label": null,
          "logBase": 1,
          "max": null,
          "min": null,
          "show": true
        }
      ],
      "yaxis": {
        "align": false,
        "alignLevel": null
      }
    },
    {
      "alert": {
        "alertRuleTags": {},
        "conditions": [
          {
            "evaluator": {
              "params": [],
              "type": "no_value"
            },
            "operator": {
              "type": "and"
            },
            "query": {
              "params": [
                "A",
                "5m",
                "now"
              ]
            },
            "reducer": {
              "params": [],
              "type": "last"
            },
            "type": "query"
          }
        ],
        "executionErrorState": "alerting",
        "for": "5m",
        "frequency": "1m",
        "handler": 1,
        "message": "RAM alert!",
        "name": "RAM alert",
        "noDataState": "keep_state",
        "notifications": []
      },
      "aliasColors": {},
      "bars": false,
      "dashLength": 10,
      "dashes": false,
      "datasource": null,
      "fieldConfig": {
        "defaults": {
          "color": {},
          "custom": {},
          "thresholds": {
            "mode": "absolute",
            "steps": []
          }
        },
        "overrides": []
      },
      "fill": 1,
      "fillGradient": 0,
      "gridPos": {
        "h": 8,
        "w": 12,
        "x": 12,
        "y": 0
      },
      "hiddenSeries": false,
      "id": 6,
      "legend": {
        "avg": false,
        "current": false,
        "max": false,
        "min": false,
        "show": true,
        "total": false,
        "values": false
      },
      "lines": true,
      "linewidth": 1,
      "nullPointMode": "null",
      "options": {
        "alertThreshold": true
      },
      "percentage": false,
      "pluginVersion": "7.4.0",
      "pointradius": 2,
      "points": false,
      "renderer": "flot",
      "seriesOverrides": [],
      "spaceLength": 10,
      "stack": false,
      "steppedLine": false,
      "targets": [
        {
          "expr": "node_memory_MemFree_bytes{job=\"nodeexporter\"}",
          "interval": "",
          "legendFormat": "RAM",
          "queryType": "randomWalk",
          "refId": "A"
        }
      ],
      "thresholds": [],
      "timeFrom": null,
      "timeRegions": [],
      "timeShift": null,
      "title": "RAM",
      "tooltip": {
        "shared": true,
        "sort": 0,
        "value_type": "individual"
      },
      "type": "graph",
      "xaxis": {
        "buckets": null,
        "mode": "time",
        "name": null,
        "show": true,
        "values": []
      },
      "yaxes": [
        {
          "format": "short",
          "label": null,
          "logBase": 1,
          "max": null,
          "min": null,
          "show": true
        },
        {
          "format": "short",
          "label": null,
          "logBase": 1,
          "max": null,
          "min": null,
          "show": true
        }
      ],
      "yaxis": {
        "align": false,
        "alignLevel": null
      }
    },
    {
      "alert": {
        "alertRuleTags": {},
        "conditions": [
          {
            "evaluator": {
              "params": [],
              "type": "no_value"
            },
            "operator": {
              "type": "and"
            },
            "query": {
              "params": [
                "A",
                "5m",
                "now"
              ]
            },
            "reducer": {
              "params": [],
              "type": "last"
            },
            "type": "query"
          }
        ],
        "executionErrorState": "alerting",
        "for": "15m",
        "frequency": "1m",
        "handler": 1,
        "message": "CPULA",
        "name": "CPULA 1/5/15 alert",
        "noDataState": "no_data",
        "notifications": []
      },
      "aliasColors": {},
      "bars": false,
      "dashLength": 10,
      "dashes": false,
      "datasource": null,
      "fieldConfig": {
        "defaults": {
          "color": {},
          "custom": {},
          "thresholds": {
            "mode": "absolute",
            "steps": []
          },
          "unit": "short"
        },
        "overrides": []
      },
      "fill": 1,
      "fillGradient": 0,
      "gridPos": {
        "h": 8,
        "w": 12,
        "x": 0,
        "y": 8
      },
      "hiddenSeries": false,
      "id": 4,
      "legend": {
        "avg": false,
        "current": false,
        "max": false,
        "min": false,
        "show": true,
        "total": false,
        "values": false
      },
      "lines": true,
      "linewidth": 1,
      "nullPointMode": "null",
      "options": {
        "alertThreshold": true
      },
      "percentage": false,
      "pluginVersion": "7.4.0",
      "pointradius": 2,
      "points": false,
      "renderer": "flot",
      "seriesOverrides": [],
      "spaceLength": 10,
      "stack": false,
      "steppedLine": false,
      "targets": [
        {
          "expr": "avg by (instance)(rate(node_load1{}[$__rate_interval]))",
          "interval": "",
          "legendFormat": "Load average 1 min",
          "queryType": "randomWalk",
          "refId": "A"
        },
        {
          "expr": "avg by (instance)(rate(node_load5{}[$__rate_interval]))",
          "hide": false,
          "interval": "",
          "legendFormat": "Load average 5 min",
          "refId": "B"
        },
        {
          "expr": "avg by (instance)(rate(node_load15{}[$__rate_interval]))",
          "hide": false,
          "interval": "",
          "legendFormat": "Load average 15 min",
          "refId": "C"
        }
      ],
      "thresholds": [],
      "timeFrom": null,
      "timeRegions": [],
      "timeShift": null,
      "title": "CPULA 1/5/15",
      "tooltip": {
        "shared": true,
        "sort": 0,
        "value_type": "individual"
      },
      "type": "graph",
      "xaxis": {
        "buckets": null,
        "mode": "time",
        "name": null,
        "show": true,
        "values": []
      },
      "yaxes": [
        {
          "format": "short",
          "label": null,
          "logBase": 1,
          "max": null,
          "min": null,
          "show": true
        },
        {
          "format": "short",
          "label": null,
          "logBase": 1,
          "max": null,
          "min": null,
          "show": true
        }
      ],
      "yaxis": {
        "align": false,
        "alignLevel": null
      }
    },
    {
      "datasource": null,
      "fieldConfig": {
        "defaults": {
          "color": {
            "mode": "thresholds"
          },
          "custom": {},
          "mappings": [],
          "thresholds": {
            "mode": "absolute",
            "steps": [
              {
                "color": "green",
                "value": null
              },
              {
                "color": "red",
                "value": 80
              }
            ]
          }
        },
        "overrides": []
      },
      "gridPos": {
        "h": 8,
        "w": 12,
        "x": 12,
        "y": 8
      },
      "id": 2,
      "options": {
        "reduceOptions": {
          "calcs": [
            "lastNotNull"
          ],
          "fields": "",
          "values": false
        },
        "showThresholdLabels": false,
        "showThresholdMarkers": true,
        "text": {}
      },
      "pluginVersion": "7.4.0",
      "targets": [
        {
          "expr": "avg by(instance)(rate(node_cpu_seconds_total{job=\"nodeexporter\",mode=\"idle\"}[$__rate_interval])) * 100",
          "interval": "",
          "legendFormat": "",
          "queryType": "randomWalk",
          "refId": "A"
        }
      ],
      "title": "CPU",
      "type": "gauge"
    }
  ],
  "refresh": false,
  "schemaVersion": 27,
  "style": "dark",
  "tags": [],
  "templating": {
    "list": []
  },
  "time": {
    "from": "2023-03-24T10:43:11.021Z",
    "to": "2023-03-24T12:29:02.397Z"
  },
  "timepicker": {},
  "timezone": "",
  "title": "Netology dashboard",
  "uid": "sfLgO5BVz",
  "version": 11
}
